HW_Adder/RCA8/RCA8_generated.v

module FA (
    input a,        // First input bit
    input b,        // Second input bit
    input cin,      // Carry input
    output sum,     // Sum output
    output cout     // Carry output
);
    wire w0;        // Intermediate wire for sum calculation

    // Sum output: sum = a XOR b XOR cin
    assign w0 = a ^ b;
    assign sum = w0 ^ cin;

    // Carry output: cout = (a AND b) OR (cin AND (a XOR b))
    assign cout = (a & b) | (cin & w0);
endmodule

// 8-bit Ripple Carry Adder Module
module RCA8 (
    input [7:0] a,  // First 8-bit input
    input [7:0] b,  // Second 8-bit input
    output [7:0] sum, // 8-bit sum output
    output cout      // 1-bit carry out
);
    wire [7:0] c;   // Internal carry signals

    // Instantiate the 1st Full Adder
    FA fa0 (
        .a(a[0]),
        .b(b[0]),
        .cin(1'b0),     // Initial carry-in is 0
        .sum(sum[0]),
        .cout(c[1])     // Carry-out to the next stage
    );

    // Instantiate the 2nd to 7th Full Adders using a generate loop
    genvar i;
    generate
        for (i = 1; i < 7; i = i + 1) begin: full_adder_array
            FA faN (
                .a(a[i]),
                .b(b[i]),
                .cin(c[i]),    // Previous stage's carry-out
                .sum(sum[i]),
                .cout(c[i + 1]) // Carry-out to the next stage
            );
        end
    endgenerate

    // Instantiate the 8th Full Adder
    FA fa7 (
        .a(a[7]),
        .b(b[7]),
        .cin(c[7]),     // Carry from the 7th stage
        .sum(sum[7]),
        .cout(cout)     // Final carry-out
    );
endmodule

HW_Adder/RCA8/RCA8_tb.v
`timescale 1ns/1ps

module RCA8_tb;

    reg  [7:0] a;
    reg  [7:0] b;
    wire [7:0] sum;
    wire       cout;

    integer total_tests;
    integer passed_tests;

    reg  [8:0] expected_fullsum;
    reg  [7:0] expected_sum;
    reg        expected_cout;
    reg  [7:1] expected_c;

    // DUT instantiation
    RCA8 dut (
        .a(a),
        .b(b),
        .sum(sum),
        .cout(cout)
    );

    // Task to compute expected internal carries for RCA
    task compute_expected_carries;
        input  [7:0] ta;
        input  [7:0] tb;
        output [7:1] tc;
        reg carry;
        integer i;
        begin
            carry = 1'b0;
            for (i = 0; i < 7; i = i + 1) begin
                carry = (ta[i] & tb[i]) | (carry & (ta[i] ^ tb[i]));
                tc[i+1] = carry;
            end
        end
    endtask

    // Task to run one test case
    task run_test;
        input [7:0] ta;
        input [7:0] tb;
        begin
            a = ta;
            b = tb;
            #1;

            total_tests = total_tests + 1;

            expected_fullsum = ta + tb;
            expected_sum     = expected_fullsum[7:0];
            expected_cout    = expected_fullsum[8];
            compute_expected_carries(ta, tb, expected_c);

            $display("--------------------------------------------------");
            $display("TEST %0d", total_tests);
            $display("a = 0x%0h (%08b), b = 0x%0h (%08b)", ta, ta, tb, tb);
            $display("Expected: sum = %08b, cout = %b, c = %b",
                     expected_sum, expected_cout, expected_c);
            $display("Actual  : sum = %08b, cout = %b, c = %b",
                     sum, cout, dut.c[7:1]);

            if ((sum === expected_sum) &&
                (cout === expected_cout) &&
                (dut.c[7:1] === expected_c)) begin
                passed_tests = passed_tests + 1;
                $display("Result  : PASS");
            end else begin
                $display("Result  : FAIL");
                if (sum !== expected_sum)
                    $display("  Mismatch in sum");
                if (cout !== expected_cout)
                    $display("  Mismatch in cout");
                if (dut.c[7:1] !== expected_c)
                    $display("  Mismatch in internal carries");
            end
        end
    endtask

    initial begin
        $dumpfile("RCA8_tb.vcd");
        $dumpvars(0, RCA8_tb);

        total_tests  = 0;
        passed_tests = 0;

        // Representative directed tests
        run_test(8'h00, 8'h00);
        run_test(8'h01, 8'h01);
        run_test(8'h0F, 8'h01);
        run_test(8'hFF, 8'h01);
        run_test(8'hAA, 8'h55);
        run_test(8'h7F, 8'h01);
        run_test(8'h80, 8'h80);
        run_test(8'hF0, 8'h0F);
        run_test(8'h3C, 8'h42);
        run_test(8'h99, 8'h66);

        // A few random tests
        run_test(8'h12, 8'h34);
        run_test(8'h5A, 8'hA5);
        run_test(8'hC3, 8'h3C);
        run_test(8'hFE, 8'h02);
        run_test(8'h81, 8'h7F);

        $display("==================================================");
        $display("SUMMARY: %0d / %0d tests passed", passed_tests, total_tests);

        if (passed_tests == total_tests)
            $display("@@@PASS");
        else
            $display("@@@FAIL");

        $finish;
    end

endmodule

HW_Adder/RCA8/RCA8_tb.vcd
$date
	Sun Apr 12 18:47:38 2026
$end
$version
	Icarus Verilog
$end
$timescale
	1ps
$end
$scope module RCA8_tb $end
$var wire 8 ! sum [7:0] $end
$var wire 1 " cout $end
$var reg 8 # a [7:0] $end
$var reg 8 $ b [7:0] $end
$var reg 7 % expected_c [7:1] $end
$var reg 1 & expected_cout $end
$var reg 9 ' expected_fullsum [8:0] $end
$var reg 8 ( expected_sum [7:0] $end
$var integer 32 ) passed_tests [31:0] $end
$var integer 32 * total_tests [31:0] $end
$scope module dut $end
$var wire 8 + a [7:0] $end
$var wire 8 , b [7:0] $end
$var wire 8 - sum [7:0] $end
$var wire 1 " cout $end
$var wire 8 . c [7:0] $end
$scope begin full_adder_array[1] $end
$scope module faN $end
$var wire 1 / a $end
$var wire 1 0 b $end
$var wire 1 1 cin $end
$var wire 1 2 cout $end
$var wire 1 3 sum $end
$var wire 1 4 w0 $end
$upscope $end
$upscope $end
$scope begin full_adder_array[2] $end
$scope module faN $end
$var wire 1 5 a $end
$var wire 1 6 b $end
$var wire 1 7 cin $end
$var wire 1 8 cout $end
$var wire 1 9 sum $end
$var wire 1 : w0 $end
$upscope $end
$upscope $end
$scope begin full_adder_array[3] $end
$scope module faN $end
$var wire 1 ; a $end
$var wire 1 < b $end
$var wire 1 = cin $end
$var wire 1 > cout $end
$var wire 1 ? sum $end
$var wire 1 @ w0 $end
$upscope $end
$upscope $end
$scope begin full_adder_array[4] $end
$scope module faN $end
$var wire 1 A a $end
$var wire 1 B b $end
$var wire 1 C cin $end
$var wire 1 D cout $end
$var wire 1 E sum $end
$var wire 1 F w0 $end
$upscope $end
$upscope $end
$scope begin full_adder_array[5] $end
$scope module faN $end
$var wire 1 G a $end
$var wire 1 H b $end
$var wire 1 I cin $end
$var wire 1 J cout $end
$var wire 1 K sum $end
$var wire 1 L w0 $end
$upscope $end
$upscope $end
$scope begin full_adder_array[6] $end
$scope module faN $end
$var wire 1 M a $end
$var wire 1 N b $end
$var wire 1 O cin $end
$var wire 1 P cout $end
$var wire 1 Q sum $end
$var wire 1 R w0 $end
$upscope $end
$upscope $end
$scope module fa0 $end
$var wire 1 S a $end
$var wire 1 T b $end
$var wire 1 U cin $end
$var wire 1 V cout $end
$var wire 1 W sum $end
$var wire 1 X w0 $end
$upscope $end
$scope module fa7 $end
$var wire 1 Y a $end
$var wire 1 Z b $end
$var wire 1 [ cin $end
$var wire 1 " cout $end
$var wire 1 \ sum $end
$var wire 1 ] w0 $end
$upscope $end
$upscope $end
$scope task compute_expected_carries $end
$var reg 1 ^ carry $end
$var reg 8 _ ta [7:0] $end
$var reg 8 ` tb [7:0] $end
$var reg 7 a tc [7:1] $end
$var integer 32 b i [31:0] $end
$upscope $end
$scope task run_test $end
$var reg 8 c ta [7:0] $end
$var reg 8 d tb [7:0] $end
$upscope $end
$upscope $end
$enddefinitions $end
#0
$dumpvars
b0 d
b0 c
bx b
bx a
bx `
bx _
x^
0]
0\
0[
0Z
0Y
0X
0W
0V
0U
0T
0S
0R
0Q
0P
0O
0N
0M
0L
0K
0J
0I
0H
0G
0F
0E
0D
0C
0B
0A
0@
0?
0>
0=
0<
0;
0:
09
08
07
06
05
04
03
02
01
00
0/
b0z .
b0 -
b0 ,
b0 +
b0 *
b0 )
bx (
bx '
x&
bx %
b0 $
b0 #
0"
b0 !
$end
#1000
b10 !
b10 -
13
11
b1z .
1V
1T
1S
b1 $
b1 ,
b1 #
b1 +
b1 d
b1 c
b1 )
b0 %
b0 a
b111 b
0^
b0 `
b0 _
0&
b0 (
b0 '
b1 *
#2000
1E
1C
1>
1=
18
17
b1111z .
12
03
09
b10000 !
b10000 -
0?
14
1:
1@
1/
15
1;
b1111 #
b1111 +
b1111 c
b10 )
b1 %
b1 a
0^
b111 b
b1 `
b1 _
b10 (
b10 '
b10 *
#3000
1"
1[
1P
1O
1J
1I
b1111111z .
1D
0E
0K
0Q
b0 !
b0 -
0\
1F
1L
1R
1]
1A
1G
1M
1Y
b11111111 #
b11111111 +
b11111111 c
b11 )
b1111 %
b1111 a
0^
b111 b
b1111 _
b10000 (
b10000 '
b11 *
#4000
0"
1\
0[
0P
1Q
0O
0J
1K
0I
0D
1E
0C
0>
1?
0=
08
19
07
02
13
01
b11111111 !
b11111111 -
1W
b0z .
0V
1X
16
1B
1N
05
0A
0M
0S
b1010101 $
b1010101 ,
b10101010 #
b10101010 +
b1010101 d
b10101010 c
b100 )
b1111111 %
b1111111 a
1^
b111 b
b11111111 _
1&
b0 (
b100000000 '
b100 *
#5000
1[
1P
0Q
1O
1J
0K
1I
1D
0E
1C
1>
0?
1=
18
09
17
12
03
11
0W
b1111111z .
1V
b10000000 !
b10000000 -
1\
0X
0]
06
0B
0N
15
1A
1M
1S
0Y
b1 $
b1 ,
b1111111 #
b1111111 +
b1 d
b1111111 c
b101 )
b0 %
b0 a
b111 b
0^
b1010101 `
b10101010 _
0&
b11111111 (
b11111111 '
b101 *
#6000
0\
07
0=
0C
0I
0O
0[
02
08
0>
0D
0J
0P
01
03
09
0?
0E
0K
b0 !
b0 -
0Q
b0z .
0V
1"
04
0:
0@
0F
0L
0R
0T
1Z
0/
05
0;
0A
0G
0M
0S
1Y
b10000000 $
b10000000 ,
b10000000 #
b10000000 +
b10000000 d
b10000000 c
b110 )
b1111111 %
b1111111 a
1^
b111 b
b1 `
b1111111 _
b10000000 (
b10000000 '
b110 *
#7000
13
19
1?
1W
1\
0"
1E
1K
b11111111 !
b11111111 -
1Q
14
1:
1@
1X
1]
1F
1L
1R
10
16
1<
1T
0Z
1A
1G
1M
b1111 $
b1111 ,
b11110000 #
b11110000 +
b1111 d
b11110000 c
b111 )
b0 %
b0 a
b111 b
0^
b10000000 `
b10000000 _
1&
b0 (
b100000000 '
b111 *
#8000
0W
b1111110 !
b1111110 -
0\
0X
0]
06
0<
1N
0T
15
1;
0M
0Y
b1000010 $
b1000010 ,
b111100 #
b111100 +
b1000010 d
b111100 c
b1000 )
b111 b
b1111 `
b11110000 _
0&
b11111111 (
b11111111 '
b1000 *
#9000
1W
b11111111 !
b11111111 -
1\
1X
1]
16
1H
05
0G
1S
1Y
b1100110 $
b1100110 ,
b10011001 #
b10011001 +
b1100110 d
b10011001 c
b1001 )
b111 b
b1000010 `
b111100 _
b1111110 (
b1111110 '
b1001 *
#10000
1O
1J
0K
1I
0E
b110000z .
1D
1Q
0?
0W
b1000110 !
b1000110 -
0\
0F
0R
0@
0X
0]
00
1B
0N
1/
0;
0S
0Y
b110100 $
b110100 ,
b10010 #
b10010 +
b110100 d
b10010 c
b1010 )
b111 b
b1100110 `
b10011001 _
b11111111 (
b11111111 '
b1010 *
#11000
0O
0"
0J
1K
0[
0I
0P
1E
b0z .
0D
1W
1\
1?
b11111111 !
b11111111 -
1Q
1F
1X
1]
1@
1R
0B
1T
1Z
1;
1M
b10100101 $
b10100101 ,
b1011010 #
b1011010 +
b10100101 d
b1011010 c
b1011 )
b110000 %
b110000 a
0^
b111 b
b110100 `
b10010 _
b1000110 (
b1000110 '
b1011 *
#12000
1<
1B
0T
0Z
0;
0A
1S
1Y
b111100 $
b111100 ,
b11000011 #
b11000011 +
b111100 d
b11000011 c
b1100 )
b0 %
b0 a
b111 b
b10100101 `
b1011010 _
b11111111 (
b11111111 '
b1100 *
#13000
1"
0\
1[
1P
0Q
1O
1J
0K
1I
1D
0E
1C
1>
0?
1=
18
09
17
03
b1111110z .
12
b0 !
b0 -
0W
04
0X
10
06
0<
0B
0H
15
1;
1A
1G
0S
b10 $
b10 ,
b11111110 #
b11111110 +
b10 d
b11111110 c
b1101 )
b111 b
b111100 `
b11000011 _
b1101 *
#14000
1"
0\
1[
1P
0Q
1O
1J
0K
1I
1D
0E
1C
1>
0?
1=
18
09
17
11
b0 !
b0 -
03
12
b1111111z .
1V
14
16
1<
1B
1H
1N
1T
0/
05
0;
0A
0G
0M
1S
b1111111 $
b1111111 ,
b10000001 #
b10000001 +
b1111111 d
b10000001 c
b1110 )
b1111110 %
b1111110 a
1^
b111 b
b10 `
b11111110 _
1&
b0 (
b100000000 '
b1110 *
#15000
b1111 )
b1111111 %
b1111111 a
b111 b
1^
b1111111 `
b10000001 _
b1111 *
